UikitZhongwenWendang/README.md
UikitZhongwenWendang/__init__.py
UikitZhongwenWendang/__main__.py
UikitZhongwenWendang/file.epub
UikitZhongwenWendang/index.html
UikitZhongwenWendang/css/__init__.py
UikitZhongwenWendang/css/annotations.css
UikitZhongwenWendang/css/main.css
UikitZhongwenWendang/css/normalize.css
UikitZhongwenWendang/css/popup.css
UikitZhongwenWendang/font/__init__.py
UikitZhongwenWendang/font/fontello.eot
UikitZhongwenWendang/font/fontello.svg
UikitZhongwenWendang/font/fontello.ttf
UikitZhongwenWendang/font/fontello.woff
UikitZhongwenWendang/img/__init__.py
UikitZhongwenWendang/img/annotator-glyph-sprite.png
UikitZhongwenWendang/img/annotator-icon-sprite.png
UikitZhongwenWendang/img/apple-touch-icon.png
UikitZhongwenWendang/img/cancelfullscreen.png
UikitZhongwenWendang/img/close.png
UikitZhongwenWendang/img/fullscreen.png
UikitZhongwenWendang/img/loader.gif
UikitZhongwenWendang/img/menu-icon.png
UikitZhongwenWendang/img/save.png
UikitZhongwenWendang/img/saved.png
UikitZhongwenWendang/img/settings-s.png
UikitZhongwenWendang/img/settings.png
UikitZhongwenWendang/img/star.png
UikitZhongwenWendang/js/__init__.py
UikitZhongwenWendang/js/epub.js
UikitZhongwenWendang/js/epub.min.js
UikitZhongwenWendang/js/epub.min.map
UikitZhongwenWendang/js/hooks.min.js
UikitZhongwenWendang/js/hooks.min.map
UikitZhongwenWendang/js/reader.js
UikitZhongwenWendang/js/reader.js.map
UikitZhongwenWendang/js/reader.min.js
UikitZhongwenWendang/js/reader.min.map
UikitZhongwenWendang/js/hooks/__init__.py
UikitZhongwenWendang/js/hooks/extensions/__init__.py
UikitZhongwenWendang/js/hooks/extensions/highlight.js
UikitZhongwenWendang/js/libs/__init__.py
UikitZhongwenWendang/js/libs/jquery.min.js
UikitZhongwenWendang/js/libs/localforage.min.js
UikitZhongwenWendang/js/libs/screenfull.js
UikitZhongwenWendang/js/libs/screenfull.min.js
UikitZhongwenWendang/js/libs/zip.min.js
UikitZhongwenWendang/js/plugins/__init__.py
UikitZhongwenWendang/js/plugins/hypothesis.js
uikit_zhongwen_wendang-2024.3.2.0.dist-info/METADATA
uikit_zhongwen_wendang-2024.3.2.0.dist-info/WHEEL
uikit_zhongwen_wendang-2024.3.2.0.dist-info/entry_points.txt
uikit_zhongwen_wendang-2024.3.2.0.dist-info/top_level.txt
uikit_zhongwen_wendang-2024.3.2.0.dist-info/RECORD
